ament_style_uncrustify-0.14.2.data/data/share/ament_index/resource_index/packages/ament_uncrustify
ament_style_uncrustify-0.14.2.data/data/share/ament_uncrustify/package.xml
ament_uncrustify/__init__.py
ament_uncrustify/main.py
ament_uncrustify/configuration/ament_code_style.cfg
ament_style_uncrustify-0.14.2.dist-info/METADATA
ament_style_uncrustify-0.14.2.dist-info/WHEEL
ament_style_uncrustify-0.14.2.dist-info/entry_points.txt
ament_style_uncrustify-0.14.2.dist-info/top_level.txt
ament_style_uncrustify-0.14.2.dist-info/RECORD
